aceiot_models_cli/__init__.py
aceiot_models_cli/bacnet_commands.py
aceiot_models_cli/cli.py
aceiot_models_cli/config.py
aceiot_models_cli/formatters.py
aceiot_models_cli/volttron_commands.py
aceiot_models_cli/commands/README.md
aceiot_models_cli/commands/__init__.py
aceiot_models_cli/commands/base.py
aceiot_models_cli/commands/bridge.py
aceiot_models_cli/commands/bridge_v2.py
aceiot_models_cli/commands/client.py
aceiot_models_cli/commands/decorators.py
aceiot_models_cli/commands/gateway.py
aceiot_models_cli/commands/loader.py
aceiot_models_cli/commands/point.py
aceiot_models_cli/commands/repl.py
aceiot_models_cli/commands/site.py
aceiot_models_cli/commands/utils.py
aceiot_models_cli/commands/volttron.py
aceiot_models_cli/commands/examples/bacnet_commands.py
aceiot_models_cli/commands/examples/client_commands.py
aceiot_models_cli/commands/examples/repl_commands.py
aceiot_models_cli/repl/__init__.py
aceiot_models_cli/repl/context.py
aceiot_models_cli/repl/core.py
aceiot_models_cli/repl/core_new.py
aceiot_models_cli/repl/executor.py
aceiot_models_cli/repl/executor_new.py
aceiot_models_cli/repl/parser.py
aceiot_models_cli/repl/volttron_repl.py
aceiot_models_cli/utils/__init__.py
aceiot_models_cli/utils/api_helpers.py
aceiot_models_cli-0.5.4.dist-info/METADATA
aceiot_models_cli-0.5.4.dist-info/WHEEL
aceiot_models_cli-0.5.4.dist-info/entry_points.txt
aceiot_models_cli-0.5.4.dist-info/licenses/LICENSE
aceiot_models_cli-0.5.4.dist-info/RECORD
