Metadata-Version: 2.4
Name: aceiot-models-cli
Version: 0.5.4
Summary: Command-line interface for ACE IoT Aerodrome API using aceiot-models package
Project-URL: Homepage, https://github.com/ACE-IoT-Solutions/aceiot-models-cli
Project-URL: Repository, https://github.com/ACE-IoT-Solutions/aceiot-models-cli
Project-URL: Issues, https://github.com/ACE-IoT-Solutions/aceiot-models-cli/issues
Author-email: Andrew Rodgers <andrew@aceiotsolutions.com>
License: MIT
License-File: LICENSE
Keywords: aceiot,api,bacnet,cli,iot
Classifier: Development Status :: 4 - Beta
Classifier: Intended Audience :: Developers
Classifier: License :: OSI Approved :: MIT License
Classifier: Programming Language :: Python :: 3
Classifier: Programming Language :: Python :: 3.10
Classifier: Programming Language :: Python :: 3.11
Classifier: Programming Language :: Python :: 3.12
Classifier: Programming Language :: Python :: 3.13
Classifier: Topic :: Internet :: WWW/HTTP :: Dynamic Content
Classifier: Topic :: Software Development :: Libraries :: Python Modules
Requires-Python: >=3.10
Requires-Dist: aceiot-models==0.3.4
Requires-Dist: click-repl>=0.3.0
Requires-Dist: click>=8.2.1
Requires-Dist: email-validator>=2.1.0
Requires-Dist: pandas>=2.0.0
Requires-Dist: prompt-toolkit>=3.0.0
Requires-Dist: pyarrow>=14.0.0
Requires-Dist: pyyaml>=6.0.1
Requires-Dist: requests-toolbelt>=1.0.0
Requires-Dist: requests>=2.31.0
Requires-Dist: rich>=13.7.0
